Data_Structure/LinkedList/CDLL.py
Data_Structure/LinkedList/DLL.py
Data_Structure/LinkedList/NLL.py
Data_Structure/LinkedList/SLL.py
Data_Structure/LinkedList/main.py
Data_Structure/Stack/LinkedListStack.py
Data_Structure/Stack/Stack.py
Data_Structure/Stack/test.py
LinkedList/CDLL.py
LinkedList/DLL.py
LinkedList/NLL.py
LinkedList/SLL.py
Stack/LinkedListStack.py
Stack/Stack.py
ndsjsk-0.0.1.9.dist-info/LICENSE
ndsjsk-0.0.1.9.dist-info/METADATA
ndsjsk-0.0.1.9.dist-info/WHEEL
ndsjsk-0.0.1.9.dist-info/top_level.txt
ndsjsk-0.0.1.9.dist-info/RECORD
