Metadata-Version: 2.1
Name: ndsjsk
Version: 0.0.1.9
Summary: New Data Structure for Python
Home-page: https://github.com/jsk0910/nds_jsk
Download-URL: https://github.com/jsk0910/nds_jsk/archive/refs/tags/v0.0.1.9.zip
Author: SangKyunJeon
Author-email: sangkyun.jeon@gmail.com
Classifier: Programming Language :: Python :: 3
Classifier: Operating System :: OS Independent
License-File: LICENSE
Requires-Dist: pytest
